Workbook

Sheet Ingresos
B2: INGRESOS PROYECTADOS | C2: Formula | D2: Mes 1 | E2: Mes 2 | F2: Mes 3 | G2: Mes 4 | H2: Mes 5 | I2: Mes 6 | J2: Mes 7 | K2: Mes 8 | L2: Mes 9 | M2: Mes 10 | N2: Mes 11 | O2: Mes 12 | P2: Total AÑO 1 | Q2: AÑO 2 | R2: AÑO 3 | S2: AÑO 4 | T2: AÑO 5
B3: CANTIDAD VENDIDA
B4: Dispositivo tecnológico de sueño infantil | C4: f(x) = (0.5 * Numero_mes)*Cantidad_año | D4: 0 | E4: 1 | F4: 1 | G4: 2 | H4: 2 | I4: 3 | J4: 3 | K4: 4 | L4: 4 | M4: 5 | N4: 5 | O4: 6 | P4: =SUM(D4:O4) -> 36 | Q4: =P4*2 -> 72 | R4: =P4*3 -> 108 | S4: =P4*4 -> 144 | T4: =P4*5 -> 180
B5: Suscripción premium app | C5: f(x) = ((0.5 * Numero_mes)*Cantidad_año)+acumulado de venta hasta la fecha | D5: =sum(D4) -> 0 | E5: =SUM(D4:E4) -> 1 | F5: =SUM(D4:F4) -> 2 | G5: =SUM(D4:G4) -> 4 | H5: =SUM(D4:H4) -> 6 | I5: =SUM(E4:I4) -> 9 | J5: =SUM(F4:J4) -> 11 | K5: =SUM(G4:K4) -> 14 | L5: =SUM(H4:L4) -> 16 | M5: =SUM(I4:M4) -> 19 | N5: =SUM(J4:N4) -> 21 | O5: =SUM(K4:O4) -> 24 | P5: =SUM(D5:O5) -> 127 | Q5: =Q4*5 -> 360 | R5: =R4*5 -> 540 | S5: =S4*5 -> 720 | T5: =T4*5 -> 900
B6: PRECIO DE VENTA
B7: Precio dispositivo | C7: f(x) = 38000 | D7: 38000 | E7: 38000 | F7: 38000 | G7: 38000 | H7: 38000 | I7: 38000 | J7: 38000 | K7: 38000 | L7: 38000 | M7: 38000 | N7: 38000 | O7: 38000 | P7: =SUM(D7:O7) -> 456000 | Q7: 38000 | R7: 38000 | S7: 38000 | T7: 38000
B8: Precio suscripción premium | C8: f(x) = 5000 | D8: 5000 | E8: 5000 | F8: 5000 | G8: 5000 | H8: 5000 | I8: 5000 | J8: 5000 | K8: 5000 | L8: 5000 | M8: 5000 | N8: 5000 | O8: 5000 | P8: 5000 | Q8: 5000 | R8: 5000 | S8: 5000 | T8: 5000
B9: INGRESOS POR PRODUCTO/SERVICIO
B10: Ingresos dispositivo | D10: =D4*D7 -> 0 | E10: =E4*E7 -> 38000 | F10: =F4*F7 -> 38000 | G10: =G4*G7 -> 76000 | H10: =H4*H7 -> 76000 | I10: =I4*I7 -> 114000 | J10: =J4*J7 -> 114000 | K10: =K4*K7 -> 152000 | ... O10: =O4*O7 -> 228000 | P10: =SUM(D10:O10) -> 1368000 | Q10: =Q4*Q7 -> 2736000 | R10: =R4*R7 -> 4104000 | S10: =S4*S7 -> 5472000 | T10: =T4*T7 -> 6840000
B11: Ingresos suscripción premium | D11: =D5*D8 -> 0 | E11: =E5*E8 -> 5000 | F11: =F5*F8 -> 10000 | G11: =G5*G8 -> 20000 | H11: =H5*H8 -> 30000 | I11: =I5*I8 -> 45000 | J11: =J5*J8 -> 55000 | K11: =K5*K8 -> 70000 | ... O11: =O5*O8 -> 120000 | P11: =SUM(D11:O11) -> 635000 | Q11: =Q5*Q8 -> 1800000 | R11: =R5*R8 -> 2700000 | S11: =S5*S8 -> 3600000 | T11: =T5*T8 -> 4500000
B12: INGRESOS TOTALES | C12: Suma de valor por cantidad respectivamente | D12: =SUM(D10:D11) -> 0 | E12: =SUM(E10:E11) -> 43000 | F12: =SUM(F10:F11) -> 48000 | G12: =SUM(G10:G11) -> 96000 | H12: =SUM(H10:H11) -> 106000 | I12: =SUM(I10:I11) -> 159000 | J12: =SUM(J10:J11) -> 169000 | K12: =SUM(K10:K11) -> 222000 | ... T12: =SUM(T10:T11) -> 11340000
B14: EGRESOS PROYECTADOS | C14: Formula | D14: Mes 1 | E14: Mes 2 | F14: Mes 3 | G14: Mes 4 | H14: Mes 5 | I14: Mes 6 | J14: Mes 7 | K14: Mes 8 | L14: Mes 9 | M14: Mes 10 | N14: Mes 11 | O14: Mes 12 | P14: Total AÑO 1 | Q14: AÑO 2 | R14: AÑO 3 | S14: AÑO 4 | T14: AÑO 5
B15: COSTOS DE PRODUCCIÓN | D15: =SUM(D16:D19) -> 50000 | E15: =SUM(E16:E19) -> 73000 | F15: =SUM(F16:F19) -> 73000 | G15: =SUM(G16:G19) -> 96000 | H15: =SUM(H16:H19) -> 96000 | I15: =SUM(I16:I19) -> 119000 | J15: =SUM(J16:J19) -> 119000 | K15: =SUM(K16:K19) -> 142000 | ... O15: =SUM(O16:O19) -> 188000 | P15: =SUM(D15:O15) -> 1428000 | Q15: =SUM(Q16:Q19) -> 2256000 | R15: =SUM(R16:R19) -> 3084000 | S15: =SUM(S16:S19) -> 3912000 | T15: =SUM(T16:T19) -> 4740000
B16: Hardware: parlante, elemento de vibración, carcasa y controlador. | C16: f(x) = (Cantidad_vendida * 18.000) | D16: =D4*18000 -> 0 | E16: =E4*18000 -> 18000 | F16: =F4*18000 -> 18000 | G16: =G4*18000 -> 36000 | H16: =H4*18000 -> 36000 | I16: =I4*18000 -> 54000 | J16: =J4*18000 -> 54000 | K16: =K4*18000 -> 72000 | ... T16: =T4*18000 -> 3240000
B17: Producción y manufactura a escala. | C17: f(x) = (Cantidad_vendida * 4000) | D17: =D4*4000 -> 0 | E17: =E4*4000 -> 4000 | F17: =F4*4000 -> 4000 | G17: =G4*4000 -> 8000 | H17: =H4*4000 -> 8000 | I17: =I4*4000 -> 12000 | J17: =J4*4000 -> 12000 | K17: =K4*4000 -> 16000 | ... T17: =T4*4000 -> 720000
B18: Desarrollo de software: app, algoritmo y plataforma de suscripción. | D18: 50000 | E18: 50000 | F18: 50000 | G18: 50000 | H18: 50000 | I18: 50000 | J18: 50000 | K18: 50000 | L18: 50000 | M18: 50000 | N18: 50000 | O18: 50000 | P18: =SUM(D18:O18) -> 600000 | Q18: 600000 | R18: 600000 | S18: 600000 | T18: 600000
B19: Packaging | C19: f(x) = (Cantidad_vendida * 1000) | D19: =D4*1000 -> 0 | E19: =E4*1000 -> 1000 | F19: =F4*1000 -> 1000 | G19: =G4*1000 -> 2000 | H19: =H4*1000 -> 2000 | I19: =I4*1000 -> 3000 | J19: =J4*1000 -> 3000 | K19: =K4*1000 -> 4000 | ... O19: =O4*1000 -> 6000 | P19: =SUM(D19:O19) -> 36000 | Q19: =P19*2 -> 72000 | R19: =R4*1000 -> 108000 | S19: =S4*1000 -> 144000 | T19: =T4*1000 -> 180000
B20: GASTOS OPERATIVOS | D20: =SUM(D21:D23) -> 0 | E20: =SUM(E21:E23) -> 5000 | F20: =SUM(F21:F23) -> 5000 | G20: =SUM(G21:G23) -> 10000 | H20: =SUM(H21:H23) -> 10000 | I20: =SUM(I21:I23) -> 15000 | J20: =SUM(J21:J23) -> 15000 | K20: =SUM(K21:K23) -> 20000 | ... O20: =SUM(O21:O23) -> 30000 | P20: =SUM(D20:O20) -> 180000 | Q20: =SUM(Q21:Q23) -> 560000 | R20: =SUM(R21:R23) -> 940000 | S20: =SUM(S21:S23) -> 1520000 | T20: =SUM(T21:T23) -> 2500000
B21: Marketing digital. | C21: f(x) = 0 (el primer año) y 100000*(año-1) | D21: 0 | E21: 0 | F21: 0 | G21: 0 | H21: 0 | I21: 0 | J21: 0 | K21: 0 | L21: 0 | M21: 0 | N21: 0 | O21: 0 | P21: =SUM(D21:O21) -> 0 | Q21: 100000 | R21: =Q21*2 -> 200000 | S21: =R21*2 -> 400000 | T21: =S21*2 -> 800000
B22: Distribución del producto. | C22: f(x) = (Cantidad_vendida * 5000) | D22: =D4*5000 -> 0 | E22: =E4*5000 -> 5000 | F22: =F4*5000 -> 5000 | G22: =G4*5000 -> 10000 | H22: =H4*5000 -> 10000 | I22: =I4*5000 -> 15000 | J22: =J4*5000 -> 15000 | K22: =K4*5000 -> 20000 | ... T22: =T4*5000 -> 900000
B23: Muestras para canal médico (pediatras/matronas). | C23: f(x) = 0 (el primer año) y 100000*(año-1) | D23: 0 | E23: 0 | F23: 0 | G23: 0 | H23: 0 | I23: 0 | J23: 0 | K23: 0 | L23: 0 | M23: 0 | N23: 0 | O23: 0 | P23: =SUM(D23:O23) -> 0 | Q23: 100000 | R23: =Q23*2 -> 200000 | S23: =R23*2 -> 400000 | T23: =S23*2 -> 800000
B24: EGRESOS OPERACIONALES TOTALES | C24: Suma de costos + gastos | D24: =D15+D20 -> 50000 | E24: =E15+E20 -> 78000 | F24: =F15+F20 -> 78000 | G24: =G15+G20 -> 106000 | H24: =H15+H20 -> 106000 | I24: =I15+I20 -> 134000 | J24: =J15+J20 -> 134000 | K24: =K15+K20 -> 162000 | ... T24: =T15+T20 -> 7240000
B26: RESUMEN | C26: Formula | D26: Mes 1 | E26: Mes 2 | F26: Mes 3 | G26: Mes 4 | H26: Mes 5 | I26: Mes 6 | J26: Mes 7 | K26: Mes 8 | L26: Mes 9 | M26: Mes 10 | N26: Mes 11 | O26: Mes 12 | P26: AÑO 1 | Q26: AÑO 2 | R26: AÑO 3 | S26: AÑO 4 | T26: AÑO 5
B27: INGRESOS TOTALES | D27: =D12 -> 0 | E27: =E12 -> 43000 | F27: =F12 -> 48000 | G27: =G12 -> 96000 | H27: =H12 -> 106000 | I27: =I12 -> 159000 | J27: =J12 -> 169000 | K27: =K12 -> 222000 | ... T27: =T12 -> 11340000
B28: COSTOS DE PRODUCCIÓN | D28: =D15 -> 50000 | E28: =E15 -> 73000 | F28: =F15 -> 73000 | G28: =G15 -> 96000 | H28: =H15 -> 96000 | I28: =I15 -> 119000 | J28: =J15 -> 119000 | K28: =K15 -> 142000 | ... T28: =T15 -> 4740000
B29: UTILIDAD BRUTA | C29: Ingreso Totales - Costos de Producción | D29: =D27-D28 -> -50000 | E29: =E27-E28 -> -30000 | F29: =F27-F28 -> -25000 | G29: =G27-G28 -> 0 | H29: =H27-H28 -> 10000 | I29: =I27-I28 -> 40000 | J29: =J27-J28 -> 50000 | K29: =K27-K28 -> 80000 | ... T29: =T27-T28 -> 6600000
B30: GASTOS OPERATIVOS | D30: =D20 -> 0 | E30: =E20 -> 5000 | F30: =F20 -> 5000 | G30: =G20 -> 10000 | H30: =H20 -> 10000 | I30: =I20 -> 15000 | J30: =J20 -> 15000 | K30: =K20 -> 20000 | ... T30: =T20 -> 2500000
B31: EGRESOS OPERACIONALES TOTALES | D31: =D24 -> 50000 | E31: =D24 -> 50000 | F31: =F28+F30 -> 78000 | G31: =G28+G30 -> 106000 | H31: =H28+H30 -> 106000 | I31: =I28+I30 -> 134000 | J31: =J28+J30 -> 134000 | K31: =K28+K30 -> 162000 | L31: =L28+L30 -> 162000 | M31: =M28+M30 -> 190000 | ... T31: =T28+T30 -> 7240000
B32: UTILIDAD OPERACIONAL / EBITDA | C32: Ingreso Totales - Egreso Operacionales Totales | D32: =D27-D31 -> -50000 | E32: =E27-E31 -> -7000 | F32: =F27-F31 -> -30000 | G32: =G27-G31 -> -10000 | H32: =H27-H31 -> 0 | I32: =I27-I31 -> 25000 | J32: =J27-J31 -> 35000 | K32: =K27-K31 -> 60000 | ... T32: =T27-T31 -> 4100000
H33: Breakeven | K33: Payback

Sheet Egresos
A1: PROYECTO: Dispositivo tecnológico de inducción del sueño infantil
A4: EGRESOS PROYECTADOS | B4: Formula | C4: Mes 1 | D4: Mes 2 | E4: Mes 3 | F4: Mes 4 | G4: Mes 5 | H4: Mes 6 | I4: Mes 7 | J4: Mes 8 | K4: Mes 9 | L4: Mes 10 | M4: Mes 11 | N4: Mes 12 | O4: Total AÑO 1 | P4: AÑO 2 | Q4: AÑO 3 | R4: AÑO 4 | S4: AÑO 5
A5: COSTOS DE PRODUCCIÓN | C5: =SUM(C6:C9) -> 50000 | D5: =SUM(D6:D9) -> 73000 | E5: =SUM(E6:E9) -> 73000 | F5: =SUM(F6:F9) -> 96000 | G5: =SUM(G6:G9) -> 96000 | H5: =SUM(H6:H9) -> 119000 | I5: =SUM(I6:I9) -> 119000 | J5: =SUM(J6:J9) -> 142000 | ... N5: =SUM(N6:N9) -> 188000 | O5: =SUM(C5:N5) -> 1428000 | P5: =SUM(P6:P9) -> 2256000 | Q5: =SUM(Q6:Q9) -> 3912000 | R5: =SUM(R6:R9) -> 7224000 | S5: =SUM(S6:S9) -> 13848000
A6: Hardware: parlante, elemento de vibración, carcasa y controlador. | B6: f(x) = (Cantidad_vendida * 18.000)*año | C6: =Ingresos!D4*18000 -> 0 | D6: =Ingresos!E4*18000 -> 18000 | E6: =Ingresos!F4*18000 -> 18000 | F6: =Ingresos!G4*18000 -> 36000 | G6: =Ingresos!H4*18000 -> 36000 | H6: =Ingresos!I4*18000 -> 54000 | I6: =Ingresos!J4*18000 -> 54000 | J6: =Ingresos!K4*18000 -> 72000 | ... N6: =Ingresos!O4*18000 -> 108000 | O6: =SUM(C6:N6) -> 648000 | P6: =O6*2 -> 1296000 | Q6: =P6*2 -> 2592000 | R6: =Q6*2 -> 5184000 | S6: =R6*2 -> 10368000
A7: Producción del prototipo y manufactura a escala. | B7: f(x) = (Cantidad_vendida * 4000)*año | C7: =Ingresos!D4*4000 -> 0 | D7: =Ingresos!E4*4000 -> 4000 | E7: =Ingresos!F4*4000 -> 4000 | F7: =Ingresos!G4*4000 -> 8000 | G7: =Ingresos!H4*4000 -> 8000 | H7: =Ingresos!I4*4000 -> 12000 | I7: =Ingresos!J4*4000 -> 12000 | J7: =Ingresos!K4*4000 -> 16000 | ... N7: =Ingresos!O4*4000 -> 24000 | O7: =SUM(C7:N7) -> 144000 | P7: =O7*2 -> 288000 | Q7: =P7*2 -> 576000 | R7: =Q7*2 -> 1152000 | S7: =R7*2 -> 2304000
A8: Desarrollo de software: app, algoritmo y plataforma de suscripción. | C8: 50000 | D8: 50000 | E8: 50000 | F8: 50000 | G8: 50000 | H8: 50000 | I8: 50000 | J8: 50000 | K8: 50000 | L8: 50000 | M8: 50000 | N8: 50000 | O8: =SUM(C8:N8) -> 600000 | P8: 600000 | Q8: 600000 | R8: 600000 | S8: 600000
A9: Packaging | B9: f(x) = (Cantidad_vendida * 1000)*año | C9: =Ingresos!D4*1000 -> 0 | D9: =Ingresos!E4*1000 -> 1000 | E9: =Ingresos!F4*1000 -> 1000 | F9: =Ingresos!G4*1000 -> 2000 | G9: =Ingresos!H4*1000 -> 2000 | H9: =Ingresos!I4*1000 -> 3000 | I9: =Ingresos!J4*1000 -> 3000 | J9: =Ingresos!K4*1000 -> 4000 | ... N9: =Ingresos!O4*1000 -> 6000 | O9: =SUM(C9:N9) -> 36000 | P9: =O9*2 -> 72000 | Q9: =P9*2 -> 144000 | R9: =Q9*2 -> 288000 | S9: =R9*2 -> 576000
A10: GASTOS OPERATIVOS | C10: =SUM(C11:C13) -> 0 | D10: =SUM(D11:D13) -> 5000 | O10: =SUM(C10:N10) -> 5000 | P10: =SUM(P11:P13) -> 560000 | Q10: =SUM(Q11:Q13) -> 1120000 | R10: =SUM(R11:R13) -> 2240000 | S10: =SUM(S11:S13) -> 4480000
A11: Marketing digital. | B11: f(x) = 0 (el primer año) y 100*año | C11: 0 | D11: 0 | E11: 0 | F11: 0 | G11: 0 | H11: 0 | I11: 0 | J11: 0 | K11: 0 | L11: 0 | M11: 0 | N11: 0 | O11: =SUM(C11:N11) -> 0 | P11: 100000 | Q11: =P11*2 -> 200000 | R11: =Q11*2 -> 400000 | S11: =R11*2 -> 800000
A12: Distribución del producto. | B12: f(x) = (Cantidad_vendida * 5000)*año | C12: =Ingresos!D4*5000 -> 0 | D12: =Ingresos!E4*5000 -> 5000 | E12: =Ingresos!F4*5000 -> 5000 | F12: =Ingresos!G4*5000 -> 10000 | G12: =Ingresos!H4*5000 -> 10000 | H12: =Ingresos!I4*5000 -> 15000 | I12: =Ingresos!J4*5000 -> 15000 | J12: =Ingresos!K4*5000 -> 20000 | ... N12: =Ingresos!O4*5000 -> 30000 | O12: =SUM(C12:N12) -> 180000 | P12: =O12*2 -> 360000 | Q12: =P12*2 -> 720000 | R12: =Q12*2 -> 1440000 | S12: =R12*2 -> 2880000
A13: Muestras para canal médico (pediatras/matronas). | B13: f(x) = 0 (el primer año) y 100*año | C13: 0 | D13: 0 | E13: 0 | F13: 0 | G13: 0 | H13: 0 | I13: 0 | J13: 0 | K13: 0 | L13: 0 | M13: 0 | N13: 0 | O13: =SUM(C13:N13) -> 0 | P13: 100000 | Q13: =P13*2 -> 200000 | R13: =Q13*2 -> 400000 | S13: =R13*2 -> 800000
A14: EGRESOS OPERACIONALES TOTALES | C14: =C5+C10 -> 50000 | D14: =D5+D10 -> 78000 | E14: =E5+E10 -> 73000 | F14: =F5+F10 -> 96000 | G14: =G5+G10 -> 96000 | H14: =H5+H10 -> 119000 | I14: =I5+I10 -> 119000 | J14: =J5+J10 -> 142000 | ... S14: =S5+S10 -> 18328000

Sheet Flujos Totales
A1: PROYECTO: Dispositivo tecnológico de inducción del sueño infantil
B4: Mes 1 | C4: Mes 2 | D4: Mes 3 | E4: Mes 4 | F4: Mes 5 | G4: Mes 6 | H4: Mes 7 | I4: Mes 8 | J4: Mes 9 | K4: Mes 10 | L4: Mes 11 | M4: Mes 12 | N4: AÑO 1 | O4: AÑO 2 | P4: AÑO 3 | Q4: AÑO 4 | R4: AÑO 5
A5: INGRESOS TOTALES | B5: =Ingresos!D12 -> 0 | C5: =Ingresos!E12 -> 43000 | D5: =Ingresos!F12 -> 48000 | E5: =Ingresos!G12 -> 96000 | F5: =Ingresos!H12 -> 106000 | G5: =Ingresos!I12 -> 159000 | H5: =Ingresos!J12 -> 169000 | I5: =Ingresos!K12 -> 222000 | ... R5: =Ingresos!T12 -> 11340000
A6: COSTOS DE PRODUCCIÓN | B6: =Egresos!C5 -> 50000 | C6: =Egresos!D5 -> 73000 | D6: =Egresos!E5 -> 73000 | E6: =Egresos!F5 -> 96000 | F6: =Egresos!G5 -> 96000 | G6: =Egresos!H5 -> 119000 | H6: =Egresos!I5 -> 119000 | I6: =Egresos!J5 -> 142000 | ... R6: =Egresos!S5 -> 13848000
A7: UTILIDAD BRUTA | B7: =B5-B6 -> -50000 | C7: =C5-C6 -> -30000 | D7: =D5-D6 -> -25000 | E7: =E5-E6 -> 0 | F7: =F5-F6 -> 10000 | G7: =G5-G6 -> 40000 | H7: =H5-H6 -> 50000 | I7: =I5-I6 -> 80000 | ... R7: =R5-R6 -> -2508000
A8: GASTOS OPERATIVOS | B8: =Egresos!C10 -> 0 | C8: =Egresos!D10 -> 5000 | D8: =Egresos!E10 | E8: =Egresos!F10 | F8: =Egresos!G10 | G8: =Egresos!H10 | H8: =Egresos!I10 | I8: =Egresos!J10 | ... R8: =Egresos!S10 -> 4480000
A9: EGRESOS OPERACIONALES TOTALES | B9: =B6+B8 -> 50000 | C9: =C6+C8 -> 78000 | D9: =D6+D8 -> 73000 | E9: =E6+E8 -> 96000 | F9: =F6+F8 -> 96000 | G9: =G6+G8 -> 119000 | H9: =H6+H8 -> 119000 | I9: =I6+I8 -> 142000 | ... R9: =R6+R8 -> 18328000
A10: UTILIDAD OPERACIONAL / EBITDA | B10: =B5-B9 -> -50000 | C10: =C5-C9 -> -35000 | D10: =D5-D9 -> -25000 | E10: =E5-E9 -> 0 | F10: =F5-F9 -> 10000 | G10: =G5-G9 -> 40000 | H10: =H5-H9 -> 50000 | I10: =I5-I9 -> 80000 | ... R10: =R5-R9 -> -6988000
A13: 0 | B13: 1 | C13: 2 | D13: 3 | E13: 4 | F13: 5 | G13: 6 | H13: 7 | I13: 8 | J13: 9 | K13: 10 | L13: 11 | M13: 12 | N13: 24 | O13: 36 | P13: 48 | Q13: 60
A14: 0 | B14: -469800 | C14: -379500 | D14: -276600 | E14: -511100 | F14: -383000 | G14: -242300 | H14: -439000 | I14: -273100 | J14: -159700 | K14: -46300 | L14: 67100 | M14: 180500 | N14: 5130000 | O14: 23808000 | P14: 52992000 | Q14: 109492000
L17: 0 | M17: 12 | N17: 24 | O17: 36 | P17: 48 | Q17: 60
L18: 0 | M18: 180500 | N18: 5130000 | O18: 23808000 | P18: 52992000 | Q18: 109492000
